{
  "project_info": {
    "project_number": "225199737456",
    "project_id": "ielts-science",
    "storage_bucket": "ielts-science.appspot.com"
  },
  "client": [
    {
      "client_info": {
        "mobilesdk_app_id": "1:225199737456:android:05fca42acf57bdb59b42b5",
        "android_client_info": {
          "package_name": "fun.IELTSScience.app"
        }
      },
      "oauth_client": [
        {
          "client_id": "225199737456-1h4sujc4gf8hco3vn51vdd2kvg6qqph1.apps.googleusercontent.com",
          "client_type": 3
        }
      ],
      "api_key": [
        {
          "current_key": "AIzaSyAExIbfhii8aO2tEAy_FKrzK8RnAPojPv8"
        }
      ],
      "services": {
        "appinvite_service": {
          "other_platform_oauth_client": [
            {
              "client_id": "225199737456-1h4sujc4gf8hco3vn51vdd2kvg6qqph1.apps.googleusercontent.com",
              "client_type": 3
            }
          ]
        }
      }
    }
  ],
  "configuration_version": "1"
}